sdatta_learning/__init__.py
sdatta_learning/feature_engineering/__init__.py
sdatta_learning/feature_engineering/feature_engineering_general_process.py
sdatta_learning/feature_engineering/classic_time_series_features/__init__.py
sdatta_learning/feature_engineering/classic_time_series_features/cumulative_features/__init__.py
sdatta_learning/feature_engineering/classic_time_series_features/cumulative_features/config.py
sdatta_learning/feature_engineering/classic_time_series_features/cumulative_features/cumulative_features_pipline.py
sdatta_learning/feature_engineering/classic_time_series_features/cumulative_features/cumulative_features_process.py
sdatta_learning/feature_engineering/classic_time_series_features/expand_date_features/__init__.py
sdatta_learning/feature_engineering/classic_time_series_features/expand_date_features/config.py
sdatta_learning/feature_engineering/classic_time_series_features/expand_date_features/expend_date_pipline.py
sdatta_learning/feature_engineering/classic_time_series_features/expand_date_features/expend_date_process.py
sdatta_learning/feature_engineering/classic_time_series_features/lag_features/__init__.py
sdatta_learning/feature_engineering/classic_time_series_features/lag_features/lag_features_pipline.py
sdatta_learning/feature_engineering/classic_time_series_features/lag_features/lag_features_process.py
sdatta_learning/feature_engineering/encoders_features/__init__.py
sdatta_learning/feature_engineering/encoders_features/item_store_sales_encoder_features/__init__.py
sdatta_learning/feature_engineering/encoders_features/item_store_sales_encoder_features/config.py
sdatta_learning/feature_engineering/encoders_features/item_store_sales_encoder_features/item_store_sales_encoder_features_pipline.py
sdatta_learning/feature_engineering/encoders_features/item_store_sales_encoder_features/item_store_sales_encoder_features_process.py
sdatta_learning/feature_engineering/event_features/__init__.py
sdatta_learning-0.0.2.dist-info/METADATA
sdatta_learning-0.0.2.dist-info/WHEEL
sdatta_learning-0.0.2.dist-info/licenses/LICENSE
sdatta_learning-0.0.2.dist-info/RECORD
